django_altcha/__init__.py
django_altcha/static/altcha/altcha.min.js
django_altcha/static/altcha/altcha.min.js.ABOUT
django_altcha/static/altcha/dist_i18n/all.min.js
django_altcha/templates/altcha_widget.html
django_altcha-0.9.0.dist-info/licenses/LICENSE
django_altcha-0.9.0.dist-info/METADATA
django_altcha-0.9.0.dist-info/WHEEL
django_altcha-0.9.0.dist-info/top_level.txt
django_altcha-0.9.0.dist-info/RECORD
