Metadata-Version: 2.4
Name: django-altcha
Version: 0.9.0
Summary: Django field and widget for Altcha CAPTCHA.
Author-email: "nexB Inc." <info@nexb.com>
License-Expression: MIT
Project-URL: Homepage, https://github.com/aboutcode-org/django-altcha
Project-URL: Documentation, https://django-altcha.readthedocs.io/
Project-URL: Repository, https://github.com/aboutcode-org/django-altcha.git
Project-URL: Issues, https://github.com/aboutcode-org/django-altcha/issues
Project-URL: Changelog, https://github.com/aboutcode-org/django-altcha/blob/main/CHANGELOG.rst
Keywords: captcha,django,widget,form,altcha
Classifier: Development Status :: 5 - Production/Stable
Classifier: Environment :: Web Environment
Classifier: Framework :: Django
Classifier: Intended Audience :: Developers
Classifier: Programming Language :: Python
Classifier: Programming Language :: Python :: 3
Classifier: Programming Language :: Python :: 3.9
Classifier: Programming Language :: Python :: 3.10
Classifier: Programming Language :: Python :: 3.11
Classifier: Programming Language :: Python :: 3.12
Classifier: Programming Language :: Python :: 3.13
Classifier: Programming Language :: Python :: 3.14
Classifier: Topic :: Software Development :: Libraries :: Python Modules
Requires-Python: >=3.9
License-File: LICENSE
Requires-Dist: Django>=4.2
Requires-Dist: altcha>=1.0.0
Provides-Extra: dev
Requires-Dist: build; extra == "dev"
Requires-Dist: ruff; extra == "dev"
Requires-Dist: pytest-django; extra == "dev"
Provides-Extra: docs
Requires-Dist: Sphinx>=5.0.2; extra == "docs"
Requires-Dist: sphinx-rtd-theme>=1.0.0; extra == "docs"
Requires-Dist: sphinx-reredirects>=0.1.2; extra == "docs"
Requires-Dist: doc8>=0.11.2; extra == "docs"
Requires-Dist: sphinx-autobuild; extra == "docs"
Requires-Dist: sphinx-rtd-dark-mode>=1.3.0; extra == "docs"
Requires-Dist: sphinx-copybutton; extra == "docs"
Requires-Dist: myst-parser; extra == "docs"
Dynamic: license-file
